treeval/__init__.py
treeval/treeval.py
treeval/utils.py
treeval/metrics/__init__.py
treeval/metrics/metrics.py
treeval-0.0.1.dist-info/METADATA
treeval-0.0.1.dist-info/WHEEL
treeval-0.0.1.dist-info/licenses/LICENSE
treeval-0.0.1.dist-info/RECORD
