Metadata-Version: 2.3
Name: treeval
Version: 0.0.1
Summary: .
Project-URL: Homepage, https://github.com/NuMindAI/Treeval
Project-URL: Repository, https://github.com/NuMindAI/Treeval.git
Project-URL: Documentation, https://treeval.readthedocs.io
Project-URL: Issues, https://github.com/NuMindAI/Treeval/issues
Author: Nathan Fradet, Liam Cripwell
License:                                  Apache License
Keywords: artificial intelligence,deep learning,evaluation,natural language generation,natural language processing,nlg,nlp,transformer
Classifier: Intended Audience :: Developers
Classifier: Intended Audience :: Science/Research
Classifier: License :: OSI Approved :: MIT License
Classifier: Operating System :: OS Independent
Classifier: Programming Language :: Python
Classifier: Programming Language :: Python :: 3 :: Only
Classifier: Programming Language :: Python :: 3.8
Classifier: Programming Language :: Python :: 3.9
Classifier: Programming Language :: Python :: 3.10
Classifier: Programming Language :: Python :: 3.11
Classifier: Programming Language :: Python :: 3.12
Classifier: Programming Language :: Python :: 3.13
Classifier: Topic :: Scientific/Engineering :: Artificial Intelligence
Requires-Python: >=3.8.0
Requires-Dist: evaluate
Requires-Dist: numpy
Requires-Dist: scipy>=1.4.0
Provides-Extra: docs
Requires-Dist: furo; extra == 'docs'
Requires-Dist: sphinx-copybutton; extra == 'docs'
Provides-Extra: tests
Requires-Dist: evaluate; extra == 'tests'
Requires-Dist: levenshtein; extra == 'tests'
Requires-Dist: pytest-cov; extra == 'tests'
Requires-Dist: pytest-xdist[psutil]; extra == 'tests'
Requires-Dist: sacrebleu; extra == 'tests'
Requires-Dist: scikit-learn; extra == 'tests'
